<DiagConfigs>
    <DcmConfig>
        <DcmGeneralConfig>
            <DcmGeneralConfig: DcmTesterResponseAddr="1"/>
            <DcmGeneralConfig: DcmTesterSourcePhyAddr="1"/>
            <DcmGeneralConfig: DcmTesterSourceFuncAddr="0"/>
            <DcmGeneralConfig: DcmDslBufferSize="4095"/>
        </DcmGeneralConfig>
        <DidConfig>
            <DidConfig: IsOnlyEol="0" DataLen="0" Did="a1a1" Operation="2"/>
            <DidConfig: IsOnlyEol="0" DataLen="11" Did="f190" Operation="2"/>
            <DidConfig: IsOnlyEol="0" DataLen="0" Did="f193" Operation="2"/>
            <DidConfig: IsOnlyEol="0" DataLen="4" Did="f195" Operation="1"/>
            <DidConfig: IsOnlyEol="0" DataLen="0" Did="f1b1" Operation="3"/>
            <DidConfig: IsOnlyEol="0" DataLen="0" Did="f187" Operation="1"/>
            <DidConfig: IsOnlyEol="0" DataLen="2000" Did="f18a" Operation="1"/>
            <DidConfig: IsOnlyEol="0" DataLen="1000" Did="f18c" Operation="3"/>
            <DidConfig: IsOnlyEol="0" DataLen="13" Did="f1a2" Operation="1"/>
            <DidConfig: IsOnlyEol="0" DataLen="4" Did="f1b5" Operation="1"/>
            <DidConfig: IsOnlyEol="0" DataLen="0" Did="f189" Operation="1"/>
            <DidConfig: IsOnlyEol="0" DataLen="0" Did="f1c0" Operation="1"/>
            <DidConfig: IsOnlyEol="0" DataLen="0" Did="f1c1" Operation="1"/>
            <DidConfig: IsOnlyEol="0" DataLen="4" Did="f299" Operation="3"/>
            <DidConfig: IsOnlyEol="0" DataLen="10" Did="f298" Operation="3"/>
            <DidConfig: IsOnlyEol="1" DataLen="2" Did="f297" Operation="3"/>
        </DidConfig>
        <RidConfig>
            <RidConfig: Rid="202" RoutineControlOptionRecord="0" RoutineType="6" Operation="15"/>
            <RidConfig: Rid="203" RoutineControlOptionRecord="0" RoutineType="6" Operation="15"/>
            <RidConfig: Rid="ff01" RoutineControlOptionRecord="0" RoutineType="6" Operation="15"/>
            <RidConfig: Rid="f103" RoutineControlOptionRecord="0" RoutineType="6" Operation="15"/>
            <RidConfig: Rid="f104" RoutineControlOptionRecord="0" RoutineType="6" Operation="15"/>
            <RidConfig: Rid="f11e" RoutineControlOptionRecord="1" RoutineType="6" Operation="15"/>
        </RidConfig>
    </DcmConfig>
    <DemConfig>
        <OpCycleConfig>
            <OpCycleConfig: Id="0" Type="0" AutoStop="0" AutoStart="0"/>
            <OpCycleConfig: Id="1" Type="0" AutoStop="0" AutoStart="0"/>
            <OpCycleConfig: Id="2" Type="0" AutoStop="0" AutoStart="0"/>
            <OpCycleConfig: Id="3" Type="0" AutoStop="1" AutoStart="1"/>
        </OpCycleConfig>
        <DebounceConfig>
            <DebounceConfig: FailedTimeThershold="100" IncStepSize="0" JumpUp="0" AlgoClass="1" JumpDown="0" JumpUpValue="0" FailedThershold="0" behavior="1" PassedTimeThershold="100" DecStepSize="0" PassedThershold="0" JumpDownValue="0"/>
            <DebounceConfig: FailedTimeThershold="0" IncStepSize="1" JumpUp="0" AlgoClass="0" JumpDown="0" JumpUpValue="0" FailedThershold="127" behavior="1" PassedTimeThershold="0" DecStepSize="-1" PassedThershold="-128" JumpDownValue="0"/>
            <DebounceConfig: FailedTimeThershold="0" IncStepSize="0" JumpUp="0" AlgoClass="3" JumpDown="0" JumpUpValue="0" FailedThershold="0" behavior="1" PassedTimeThershold="0" DecStepSize="0" PassedThershold="0" JumpDownValue="0"/>
        </DebounceConfig>
        <DTCConfig>
            <DTCConfig: AgingOpCycleRef="4" ImmediateNvStorageAllowed="0" AvailableStatus="0" AttrbsRef="0" AgingThershold="255" Id="0" OpCycleRef="4" DebounceTableRef="255" DTCTableRef="0" DemCallbackInitMForE="((void *) 0)" StorageConditionRef="0" FailureCycleCounterThershold="255" Value="ffffff" AgingAllowed="0" EventKind="0" EnableConditionRef="0"/>
            <DTCConfig: AgingOpCycleRef="0" ImmediateNvStorageAllowed="1" AvailableStatus="1" AttrbsRef="1" AgingThershold="40" Id="1" OpCycleRef="2" DebounceTableRef="255" DTCTableRef="1" DemCallbackInitMForE="((void *) 0)" StorageConditionRef="0" FailureCycleCounterThershold="255" Value="0" AgingAllowed="1" EventKind="0" EnableConditionRef="0"/>
            <DTCConfig: AgingOpCycleRef="0" ImmediateNvStorageAllowed="1" AvailableStatus="1" AttrbsRef="2" AgingThershold="40" Id="2" OpCycleRef="2" DebounceTableRef="255" DTCTableRef="2" DemCallbackInitMForE="((void *) 0)" StorageConditionRef="0" FailureCycleCounterThershold="255" Value="0" AgingAllowed="1" EventKind="1" EnableConditionRef="0"/>
            <DTCConfig: AgingOpCycleRef="0" ImmediateNvStorageAllowed="1" AvailableStatus="1" AttrbsRef="3" AgingThershold="40" Id="3" OpCycleRef="3" DebounceTableRef="1" DTCTableRef="3" DemCallbackInitMForE="((void *) 0)" StorageConditionRef="0" FailureCycleCounterThershold="255" Value="c14087" AgingAllowed="1" EventKind="0" EnableConditionRef="0"/>
            <DTCConfig: AgingOpCycleRef="3" ImmediateNvStorageAllowed="1" AvailableStatus="1" AttrbsRef="4" AgingThershold="40" Id="4" OpCycleRef="3" DebounceTableRef="0" DTCTableRef="4" DemCallbackInitMForE="((void *) 0)" StorageConditionRef="0" FailureCycleCounterThershold="255" Value="d10017" AgingAllowed="1" EventKind="0" EnableConditionRef="0"/>
            <DTCConfig: AgingOpCycleRef="3" ImmediateNvStorageAllowed="1" AvailableStatus="1" AttrbsRef="5" AgingThershold="40" Id="5" OpCycleRef="3" DebounceTableRef="0" DTCTableRef="5" DemCallbackInitMForE="((void *) 0)" StorageConditionRef="0" FailureCycleCounterThershold="255" Value="d10116" AgingAllowed="1" EventKind="0" EnableConditionRef="0"/>
            <DTCConfig: AgingOpCycleRef="3" ImmediateNvStorageAllowed="1" AvailableStatus="1" AttrbsRef="6" AgingThershold="40" Id="6" OpCycleRef="3" DebounceTableRef="0" DTCTableRef="6" DemCallbackInitMForE="((void *) 0)" StorageConditionRef="0" FailureCycleCounterThershold="255" Value="c07388" AgingAllowed="1" EventKind="0" EnableConditionRef="0"/>
            <DTCConfig: AgingOpCycleRef="3" ImmediateNvStorageAllowed="1" AvailableStatus="1" AttrbsRef="7" AgingThershold="40" Id="7" OpCycleRef="3" DebounceTableRef="0" DTCTableRef="7" DemCallbackInitMForE="((void *) 0)" StorageConditionRef="0" FailureCycleCounterThershold="255" Value="900a98" AgingAllowed="1" EventKind="0" EnableConditionRef="0"/>
            <DTCConfig: AgingOpCycleRef="3" ImmediateNvStorageAllowed="1" AvailableStatus="1" AttrbsRef="8" AgingThershold="40" Id="8" OpCycleRef="3" DebounceTableRef="0" DTCTableRef="8" DemCallbackInitMForE="((void *) 0)" StorageConditionRef="0" FailureCycleCounterThershold="255" Value="900a81" AgingAllowed="1" EventKind="0" EnableConditionRef="0"/>
            <DTCConfig: AgingOpCycleRef="3" ImmediateNvStorageAllowed="1" AvailableStatus="1" AttrbsRef="9" AgingThershold="40" Id="9" OpCycleRef="3" DebounceTableRef="0" DTCTableRef="9" DemCallbackInitMForE="((void *) 0)" StorageConditionRef="0" FailureCycleCounterThershold="255" Value="900a96" AgingAllowed="1" EventKind="0" EnableConditionRef="0"/>
        </DTCConfig>
    </DemConfig>
    <NVMConfig>
        <NVMBlockConfig>
            <NVMBlockConfig: SelectBlockForReadAll="1" Str_RomBlockDataAddress="NULL" Str_JobFinishedFunction="NULL" NvBlockBaseNumber="0" NvBlockLength="0" RomBlockNum="0" Str_BlockName="NvMConf___MultiBlockRequest" NvRamBlockIdentifier="0" BlockUseCrc="0" NvBlockNum="0" NvRamDeviceId="0" BlockWriteProt="0" Str_RomBlockDefaultData="0" Str_InitFun="NULL" CalcRamBlockCrc="0" BlockJobPriority="1" BlockManagementType="0" BswMBlockStatusInformation="0" SelectBlockForWriteAll="1" MaxNumWriteRetries="0" Str_RamBlockDataAddress="NULL" MaxNumReadRetries="0" WriteBlockOnce="0" BlockUseSetRamBlockStatus="0" BlockCrcType="2"/>
            <NVMBlockConfig: SelectBlockForReadAll="1" Str_RomBlockDataAddress="NULL" Str_JobFinishedFunction="NULL" NvBlockBaseNumber="0" NvBlockLength="32" RomBlockNum="0" Str_BlockName="NvMConf_NvMBlockDescriptor_NvMConfigBlock" NvRamBlockIdentifier="0" BlockUseCrc="0" NvBlockNum="0" NvRamDeviceId="0" BlockWriteProt="0" Str_RomBlockDefaultData="0" Str_InitFun="NULL" CalcRamBlockCrc="0" BlockJobPriority="1" BlockManagementType="0" BswMBlockStatusInformation="0" SelectBlockForWriteAll="1" MaxNumWriteRetries="0" Str_RamBlockDataAddress="NvMConfigBlock_RamBlock_au8" MaxNumReadRetries="0" WriteBlockOnce="0" BlockUseSetRamBlockStatus="0" BlockCrcType="2"/>
            <NVMBlockConfig: SelectBlockForReadAll="1" Str_RomBlockDataAddress="DemCfg_OpCycle_Default" Str_JobFinishedFunction="Dem_NvM_JobFinished" NvBlockBaseNumber="2" NvBlockLength="9" RomBlockNum="0" Str_BlockName="DemCfg_NvMBlockDescriptor_OpCycle" NvRamBlockIdentifier="0" BlockUseCrc="0" NvBlockNum="0" NvRamDeviceId="0" BlockWriteProt="0" Str_RomBlockDefaultData="0" Str_InitFun="NULL" CalcRamBlockCrc="0" BlockJobPriority="1" BlockManagementType="0" BswMBlockStatusInformation="0" SelectBlockForWriteAll="1" MaxNumWriteRetries="0" Str_RamBlockDataAddress="Dem_Cfg_OpCycle" MaxNumReadRetries="0" WriteBlockOnce="0" BlockUseSetRamBlockStatus="0" BlockCrcType="2"/>
            <NVMBlockConfig: SelectBlockForReadAll="1" Str_RomBlockDataAddress="DemCfg_AdminData_Default" Str_JobFinishedFunction="Dem_NvM_JobFinished" NvBlockBaseNumber="3" NvBlockLength="20" RomBlockNum="0" Str_BlockName="DemCfg_NvMBlockDescriptor_DemAdmin" NvRamBlockIdentifier="0" BlockUseCrc="0" NvBlockNum="0" NvRamDeviceId="0" BlockWriteProt="0" Str_RomBlockDefaultData="0" Str_InitFun="NULL" CalcRamBlockCrc="0" BlockJobPriority="1" BlockManagementType="0" BswMBlockStatusInformation="0" SelectBlockForWriteAll="1" MaxNumWriteRetries="0" Str_RamBlockDataAddress="Dem_Cfg_AdminData" MaxNumReadRetries="0" WriteBlockOnce="0" BlockUseSetRamBlockStatus="0" BlockCrcType="2"/>
            <NVMBlockConfig: SelectBlockForReadAll="1" Str_RomBlockDataAddress="DemCfg_StatusData_Default" Str_JobFinishedFunction="Dem_NvM_JobFinished" NvBlockBaseNumber="4" NvBlockLength="9" RomBlockNum="0" Str_BlockName="DemCfg_NvMBlockDescriptor_DemStatus" NvRamBlockIdentifier="0" BlockUseCrc="0" NvBlockNum="0" NvRamDeviceId="0" BlockWriteProt="0" Str_RomBlockDefaultData="0" Str_InitFun="NULL" CalcRamBlockCrc="0" BlockJobPriority="1" BlockManagementType="0" BswMBlockStatusInformation="0" SelectBlockForWriteAll="1" MaxNumWriteRetries="0" Str_RamBlockDataAddress="Dem_Cfg_StatusData" MaxNumReadRetries="0" WriteBlockOnce="0" BlockUseSetRamBlockStatus="0" BlockCrcType="2"/>
            <NVMBlockConfig: SelectBlockForReadAll="1" Str_RomBlockDataAddress="NvmRomData_VIN" Str_JobFinishedFunction="Rte_Call_VIN_JobFinished" NvBlockBaseNumber="5" NvBlockLength="17" RomBlockNum="0" Str_BlockName="NvMConf_NvMBlockDescriptor_VIN" NvRamBlockIdentifier="0" BlockUseCrc="0" NvBlockNum="0" NvRamDeviceId="0" BlockWriteProt="0" Str_RomBlockDefaultData="0x4C, 0x58, 0x57, 0x59, 0x45, 0x50, 0x47, 0x32, 0x38, 0x4A, 0x48, 0x30, 0x30, 0x31, 0x37, 0x35, 0x32" Str_InitFun="NULL" CalcRamBlockCrc="0" BlockJobPriority="1" BlockManagementType="0" BswMBlockStatusInformation="0" SelectBlockForWriteAll="1" MaxNumWriteRetries="0" Str_RamBlockDataAddress="NvmRamData_VIN" MaxNumReadRetries="0" WriteBlockOnce="0" BlockUseSetRamBlockStatus="0" BlockCrcType="2"/>
            <NVMBlockConfig: SelectBlockForReadAll="1" Str_RomBlockDataAddress="NvmRomData_EcuConfig" Str_JobFinishedFunction="Rte_Call_EcuConfig_JobFinished" NvBlockBaseNumber="6" NvBlockLength="200" RomBlockNum="0" Str_BlockName="NvMConf_NvMBlockDescriptor_EcuConfig" NvRamBlockIdentifier="0" BlockUseCrc="0" NvBlockNum="0" NvRamDeviceId="0" BlockWriteProt="0" Str_RomBlockDefaultData="0xFF, 0xFF, 0xFF, 0xFF, 0xFF, 0xFF, 0xFF, 0xFF, 0xFF, 0xFF, 0xFF, 0xFF, 0xFF, 0xFF, 0xFF, 0xFF, 0xFF, 0xFF, 0xFF, 0xFF,0xFF, 0xFF, 0xFF, 0xFF, 0xFF, 0xFF, 0xFF, 0xFF, 0xFF, 0xFF, 0xFF, 0xFF, 0xFF, 0xFF, 0xFF, 0xFF, 0xFF, 0xFF, 0xFF, 0xFF,0xFF, 0xFF, 0xFF, 0xFF, 0xFF, 0xFF, 0xFF, 0xFF, 0xFF, 0xFF, 0xFF, 0xFF, 0xFF, 0xFF, 0xFF, 0xFF, 0xFF, 0xFF, 0xFF, 0xFF,0xFF, 0xFF, 0xFF, 0xFF, 0xFF, 0xFF, 0xFF, 0xFF, 0xFF, 0xFF, 0xFF, 0xFF, 0xFF, 0xFF, 0xFF, 0xFF, 0xFF, 0xFF, 0xFF, 0xFF,0xFF, 0xFF, 0xFF, 0xFF, 0xFF, 0xFF, 0xFF, 0xFF, 0xFF, 0xFF, 0xFF, 0xFF, 0xFF, 0xFF, 0xFF, 0xFF, 0xFF, 0xFF, 0xFF, 0xFF,0xFF, 0xFF, 0xFF, 0xFF, 0xFF, 0xFF, 0xFF, 0xFF, 0xFF, 0xFF, 0xFF, 0xFF, 0xFF, 0xFF, 0xFF, 0xFF, 0xFF, 0xFF, 0xFF, 0xFF,0xFF, 0xFF, 0xFF, 0xFF, 0xFF, 0xFF, 0xFF, 0xFF, 0xFF, 0xFF, 0xFF, 0xFF, 0xFF, 0xFF, 0xFF, 0xFF, 0xFF, 0xFF, 0xFF, 0xFF,0xFF, 0xFF, 0xFF, 0xFF, 0xFF, 0xFF, 0xFF, 0xFF, 0xFF, 0xFF, 0xFF, 0xFF, 0xFF, 0xFF, 0xFF, 0xFF, 0xFF, 0xFF, 0xFF, 0xFF,0xFF, 0xFF, 0xFF, 0xFF, 0xFF, 0xFF, 0xFF, 0xFF, 0xFF, 0xFF, 0xFF, 0xFF, 0xFF, 0xFF, 0xFF, 0xFF, 0xFF, 0xFF, 0xFF, 0xFF,0xFF, 0xFF, 0xFF, 0xFF, 0xFF, 0xFF, 0xFF, 0xFF, 0xFF, 0xFF, 0xFF, 0xFF, 0xFF, 0xFF, 0xFF, 0xFF, 0xFF, 0xFF, 0xFF, 0xFF" Str_InitFun="NULL" CalcRamBlockCrc="0" BlockJobPriority="1" BlockManagementType="0" BswMBlockStatusInformation="0" SelectBlockForWriteAll="1" MaxNumWriteRetries="0" Str_RamBlockDataAddress="NvmRamData_EcuConfig" MaxNumReadRetries="0" WriteBlockOnce="0" BlockUseSetRamBlockStatus="0" BlockCrcType="2"/>
            <NVMBlockConfig: SelectBlockForReadAll="1" Str_RomBlockDataAddress="NvmRomData_EIDCConfig" Str_JobFinishedFunction="Rte_Call_EIDCConfig_JobFinished" NvBlockBaseNumber="7" NvBlockLength="8" RomBlockNum="0" Str_BlockName="NvMConf_NvMBlockDescriptor_EIDCConfig" NvRamBlockIdentifier="0" BlockUseCrc="0" NvBlockNum="0" NvRamDeviceId="0" BlockWriteProt="0" Str_RomBlockDefaultData="0,1,0,2,0,0,0,0" Str_InitFun="NULL" CalcRamBlockCrc="0" BlockJobPriority="1" BlockManagementType="0" BswMBlockStatusInformation="0" SelectBlockForWriteAll="1" MaxNumWriteRetries="0" Str_RamBlockDataAddress="NvmRamData_EIDCConfig" MaxNumReadRetries="0" WriteBlockOnce="0" BlockUseSetRamBlockStatus="0" BlockCrcType="2"/>
            <NVMBlockConfig: SelectBlockForReadAll="1" Str_RomBlockDataAddress="Dem_MemoryEntryInit" Str_JobFinishedFunction="Dem_NvM_JobFinished" NvBlockBaseNumber="8" NvBlockLength="24" RomBlockNum="0" Str_BlockName="DemCfg_NvMBlockDescriptor_DemPrimary_000" NvRamBlockIdentifier="0" BlockUseCrc="0" NvBlockNum="0" NvRamDeviceId="0" BlockWriteProt="0" Str_RomBlockDefaultData="0" Str_InitFun="NULL" CalcRamBlockCrc="0" BlockJobPriority="1" BlockManagementType="0" BswMBlockStatusInformation="0" SelectBlockForWriteAll="1" MaxNumWriteRetries="0" Str_RamBlockDataAddress="Dem_PrimaryEntry_000" MaxNumReadRetries="0" WriteBlockOnce="0" BlockUseSetRamBlockStatus="0" BlockCrcType="2"/>
            <NVMBlockConfig: SelectBlockForReadAll="1" Str_RomBlockDataAddress="Dem_MemoryEntryInit" Str_JobFinishedFunction="Dem_NvM_JobFinished" NvBlockBaseNumber="9" NvBlockLength="24" RomBlockNum="0" Str_BlockName="DemCfg_NvMBlockDescriptor_DemPrimary_001" NvRamBlockIdentifier="0" BlockUseCrc="0" NvBlockNum="0" NvRamDeviceId="0" BlockWriteProt="0" Str_RomBlockDefaultData="0" Str_InitFun="NULL" CalcRamBlockCrc="0" BlockJobPriority="1" BlockManagementType="0" BswMBlockStatusInformation="0" SelectBlockForWriteAll="1" MaxNumWriteRetries="0" Str_RamBlockDataAddress="Dem_PrimaryEntry_001" MaxNumReadRetries="0" WriteBlockOnce="0" BlockUseSetRamBlockStatus="0" BlockCrcType="2"/>
            <NVMBlockConfig: SelectBlockForReadAll="1" Str_RomBlockDataAddress="Dem_MemoryEntryInit" Str_JobFinishedFunction="Dem_NvM_JobFinished" NvBlockBaseNumber="10" NvBlockLength="24" RomBlockNum="0" Str_BlockName="DemCfg_NvMBlockDescriptor_DemPrimary_002" NvRamBlockIdentifier="0" BlockUseCrc="0" NvBlockNum="0" NvRamDeviceId="0" BlockWriteProt="0" Str_RomBlockDefaultData="0" Str_InitFun="NULL" CalcRamBlockCrc="0" BlockJobPriority="1" BlockManagementType="0" BswMBlockStatusInformation="0" SelectBlockForWriteAll="1" MaxNumWriteRetries="0" Str_RamBlockDataAddress="Dem_PrimaryEntry_002" MaxNumReadRetries="0" WriteBlockOnce="0" BlockUseSetRamBlockStatus="0" BlockCrcType="2"/>
            <NVMBlockConfig: SelectBlockForReadAll="1" Str_RomBlockDataAddress="Dem_MemoryEntryInit" Str_JobFinishedFunction="Dem_NvM_JobFinished" NvBlockBaseNumber="11" NvBlockLength="24" RomBlockNum="0" Str_BlockName="DemCfg_NvMBlockDescriptor_DemPrimary_003" NvRamBlockIdentifier="0" BlockUseCrc="0" NvBlockNum="0" NvRamDeviceId="0" BlockWriteProt="0" Str_RomBlockDefaultData="0" Str_InitFun="NULL" CalcRamBlockCrc="0" BlockJobPriority="1" BlockManagementType="0" BswMBlockStatusInformation="0" SelectBlockForWriteAll="1" MaxNumWriteRetries="0" Str_RamBlockDataAddress="Dem_PrimaryEntry_003" MaxNumReadRetries="0" WriteBlockOnce="0" BlockUseSetRamBlockStatus="0" BlockCrcType="2"/>
            <NVMBlockConfig: SelectBlockForReadAll="1" Str_RomBlockDataAddress="Dem_MemoryEntryInit" Str_JobFinishedFunction="Dem_NvM_JobFinished" NvBlockBaseNumber="12" NvBlockLength="24" RomBlockNum="0" Str_BlockName="DemCfg_NvMBlockDescriptor_DemPrimary_004" NvRamBlockIdentifier="0" BlockUseCrc="0" NvBlockNum="0" NvRamDeviceId="0" BlockWriteProt="0" Str_RomBlockDefaultData="0" Str_InitFun="NULL" CalcRamBlockCrc="0" BlockJobPriority="1" BlockManagementType="0" BswMBlockStatusInformation="0" SelectBlockForWriteAll="1" MaxNumWriteRetries="0" Str_RamBlockDataAddress="Dem_PrimaryEntry_004" MaxNumReadRetries="0" WriteBlockOnce="0" BlockUseSetRamBlockStatus="0" BlockCrcType="2"/>
            <NVMBlockConfig: SelectBlockForReadAll="1" Str_RomBlockDataAddress="Dem_MemoryEntryInit" Str_JobFinishedFunction="Dem_NvM_JobFinished" NvBlockBaseNumber="13" NvBlockLength="24" RomBlockNum="0" Str_BlockName="DemCfg_NvMBlockDescriptor_DemPrimary_005" NvRamBlockIdentifier="0" BlockUseCrc="0" NvBlockNum="0" NvRamDeviceId="0" BlockWriteProt="0" Str_RomBlockDefaultData="0" Str_InitFun="NULL" CalcRamBlockCrc="0" BlockJobPriority="1" BlockManagementType="0" BswMBlockStatusInformation="0" SelectBlockForWriteAll="1" MaxNumWriteRetries="0" Str_RamBlockDataAddress="Dem_PrimaryEntry_005" MaxNumReadRetries="0" WriteBlockOnce="0" BlockUseSetRamBlockStatus="0" BlockCrcType="2"/>
            <NVMBlockConfig: SelectBlockForReadAll="1" Str_RomBlockDataAddress="Dem_MemoryEntryInit" Str_JobFinishedFunction="Dem_NvM_JobFinished" NvBlockBaseNumber="14" NvBlockLength="24" RomBlockNum="0" Str_BlockName="DemCfg_NvMBlockDescriptor_DemPrimary_006" NvRamBlockIdentifier="0" BlockUseCrc="0" NvBlockNum="0" NvRamDeviceId="0" BlockWriteProt="0" Str_RomBlockDefaultData="0" Str_InitFun="NULL" CalcRamBlockCrc="0" BlockJobPriority="1" BlockManagementType="0" BswMBlockStatusInformation="0" SelectBlockForWriteAll="1" MaxNumWriteRetries="0" Str_RamBlockDataAddress="Dem_PrimaryEntry_006" MaxNumReadRetries="0" WriteBlockOnce="0" BlockUseSetRamBlockStatus="0" BlockCrcType="2"/>
        </NVMBlockConfig>
        <FEEBlockConfig>
            <FEEBlockConfig: FEE_NUM_PARTITIONS="1"/>
            <FEEBlockConfig: FEE_MAX_LENGTH="216"/>
            <FEEBlockConfig: FEE_SECTOR_SIZE="2048"/>
            <FEEBlockConfig: FEE_SECTOR_HEADER_SIZE="8"/>
            <FEEBlockConfig: FEE_SECTOR_FOOTER_SIZE="8"/>
            <FEEBlockConfig: FEE_HEADER_SIZE="8"/>
        </FEEBlockConfig>
    </NVMConfig>
</DiagConfigs>
